nlarge/__init__.py
nlarge/dataset_concat.py
nlarge/llm.py
nlarge/log.txt
nlarge/model/Attention.py
nlarge/model/GRU.py
nlarge/model/LSTM.py
nlarge/model/RNN.py
nlarge/pipeline.py
nlarge/random.py
nlarge/synonym.py
nlarge/utils/Token.py
nlarge/utils/__init__.py
nlarge/utils/words.py
nlarge-1.0.0.dist-info/METADATA
nlarge-1.0.0.dist-info/WHEEL
nlarge-1.0.0.dist-info/RECORD
